{
  "name": "skeleton-webpack-esnext-jest",
  "type": "project:application",
  "bundler": {
    "id": "webpack",
    "displayName": "Webpack"
  },
  "build": {
    "options": {
      "server": "dev",
      "extractCss": "prod",
      "coverage": false
    }
  },
  "platform": {
    "id": "web",
    "displayName": "Web"
  },
  "loader": {
    "id": "none",
    "displayName": "None"
  },
  "transpiler": {
    "id": "babel",
    "displayName": "Babel",
    "fileExtension": ".js"
  },
  "markupProcessor": {
    "id": "minimum",
    "displayName": "Minimal Minification",
    "fileExtension": ".html"
  },
  "cssProcessor": {
    "id": "none",
    "displayName": "None",
    "fileExtension": ".css"
  },
  "editor": {
    "id": "vscode",
    "displayName": "Visual Studio Code"
  },
  "unitTestRunner": {
    "id": "jest",
    "displayName": "Jest"
  },
  "integrationTestRunner": {
    "id": "protractor",
    "displayName": "Protractor"
  },
  "features": {
    "navigation": "navigation"
  }
}
